CHANGELOG.rst
LICENSE
MANIFEST.in
README.rst
contributors.txt
setup.py
django_nanolog.egg-info/PKG-INFO
django_nanolog.egg-info/SOURCES.txt
django_nanolog.egg-info/dependency_links.txt
django_nanolog.egg-info/top_level.txt
docs/examples.rst
nanolog/__init__.py
nanolog/admin.py
nanolog/models.py
nanolog/tests.py
nanolog/utils.py
nanolog/views.py